fairyfishnet.py
fairyfishnet-1.16.54.dist-info/licenses/LICENSE.txt
fairyfishnet-1.16.54.dist-info/METADATA
fairyfishnet-1.16.54.dist-info/WHEEL
fairyfishnet-1.16.54.dist-info/top_level.txt
fairyfishnet-1.16.54.dist-info/RECORD
