Metadata-Version: 2.4
Name: fairyfishnet
Version: 1.16.54
Summary: Distributed Fairy-Stockfish analysis for pychess-variants
Home-page: https://github.com/gbtami/fairyfishnet
Author: Bajusz Tamás
Author-email: gbtami@gmail.com
Keywords: lichess.org chess stockfish uci
Classifier: Development Status :: 5 - Production/Stable
Classifier: Environment :: Console
Classifier: Intended Audience :: Developers
Classifier: Intended Audience :: End Users/Desktop
Classifier: License :: OSI Approved :: GNU General Public License v3 or later (GPLv3+)
Classifier: Operating System :: OS Independent
Classifier: Programming Language :: Python
Classifier: Programming Language :: Python :: 3
Classifier: Programming Language :: Python :: 3.7
Classifier: Programming Language :: Python :: 3.8
Classifier: Programming Language :: Python :: 3.9
Classifier: Programming Language :: Python :: 3.10
Classifier: Programming Language :: Python :: 3.11
Classifier: Topic :: Games/Entertainment :: Board Games
Classifier: Topic :: Internet :: WWW/HTTP
Requires-Python: >=3.7
License-File: LICENSE.txt
Requires-Dist: requests==2.32.4
Requires-Dist: pyffish==0.0.88
Requires-Dist: gdown==5.2.0
Requires-Dist: beautifulsoup4==4.12.3
Dynamic: author
Dynamic: author-email
Dynamic: classifier
Dynamic: description
Dynamic: description-content-type
Dynamic: home-page
Dynamic: keywords
Dynamic: license-file
Dynamic: requires-dist
Dynamic: requires-python
Dynamic: summary
